markdown2pdf3/__init__.py
markdown2pdf3/main.py
markdown2pdf3/utils.py
markdown2pdf3-0.2.3.dist-info/METADATA
markdown2pdf3-0.2.3.dist-info/WHEEL
markdown2pdf3-0.2.3.dist-info/entry_points.txt
markdown2pdf3-0.2.3.dist-info/top_level.txt
markdown2pdf3-0.2.3.dist-info/RECORD
