Metadata-Version: 2.1
Name: markdown2pdf3
Version: 0.2.3
Summary: A tool converts Markdown file to PDF.
Home-page: https://github.com/panhaoyu/markdown2pdf
Author: panhaoyu
Author-email: haoyupan@aliyun.com
License: MIT
Platform: any
Classifier: Environment :: Console
Classifier: Intended Audience :: Developers
Classifier: License :: OSI Approved :: MIT License
Classifier: Operating System :: MacOS :: MacOS X
Classifier: Operating System :: POSIX :: Linux
Classifier: Topic :: Internet :: WWW/HTTP :: Dynamic Content
Classifier: Topic :: Software Development :: Libraries :: Python Modules
Classifier: Programming Language :: Python
Classifier: Programming Language :: Python :: 3
